{"data":{"recipe":{"html":"<h3>Ingredients</h3>\n<ul>\n<li>200g Chickpeas</li>\n<li>1/2 Lime</li>\n<li>1 Clove Garlic</li>\n<li>1 Cooked Redbeet</li>\n<li>1 Tsp Olive Oil</li>\n<li>Some Water</li>\n</ul>\n<h3>Instructions</h3>\n<ol>\n<li>Add chickpeas to a food processor</li>\n<li>Add garlic, juice of half a lime, olive oil</li>\n<li>Take them for a spin</li>\n<li>Add redbeet and some redbeet powder (for color)</li>\n<li>Keep spinning</li>\n<li>Add water to get desired consistence</li>\n<li>Add cumin, cayenne, salt, and pepper to taste</li>\n<li>Garnish with sesame, and serve in a bowl with nachos or veggie sticks </li>\n</ol>","htmlAst":{"type":"root","children":[{"type":"element","tagName":"h3","properties":{},"children":[{"type":"text","value":"Ingredients"}]},{"type":"text","value":"\n"},{"type":"element","tagName":"ul","properties":{},"children":[{"type":"text","value":"\n"},{"type":"element","tagName":"li","properties":{},"children":[{"type":"text","value":"200g Chickpeas"}]},{"type":"text","value":"\n"},{"type":"element","tagName":"li","properties":{},"children":[{"type":"text","value":"1/2 Lime"}]},{"type":"text","value":"\n"},{"type":"element","tagName":"li","properties":{},"children":[{"type":"text","value":"1 Clove Garlic"}]},{"type":"text","value":"\n"},{"type":"element","tagName":"li","properties":{},"children":[{"type":"text","value":"1 Cooked Redbeet"}]},{"type":"text","value":"\n"},{"type":"element","tagName":"li","properties":{},"children":[{"type":"text","value":"1 Tsp Olive Oil"}]},{"type":"text","value":"\n"},{"type":"element","tagName":"li","properties":{},"children":[{"type":"text","value":"Some Water"}]},{"type":"text","value":"\n"}]},{"type":"text","value":"\n"},{"type":"element","tagName":"h3","properties":{},"children":[{"type":"text","value":"Instructions"}]},{"type":"text","value":"\n"},{"type":"element","tagName":"ol","properties":{},"children":[{"type":"text","value":"\n"},{"type":"element","tagName":"li","properties":{},"children":[{"type":"text","value":"Add chickpeas to a food processor"}]},{"type":"text","value":"\n"},{"type":"element","tagName":"li","properties":{},"children":[{"type":"text","value":"Add garlic, juice of half a lime, olive oil"}]},{"type":"text","value":"\n"},{"type":"element","tagName":"li","properties":{},"children":[{"type":"text","value":"Take them for a spin"}]},{"type":"text","value":"\n"},{"type":"element","tagName":"li","properties":{},"children":[{"type":"text","value":"Add redbeet and some redbeet powder (for color)"}]},{"type":"text","value":"\n"},{"type":"element","tagName":"li","properties":{},"children":[{"type":"text","value":"Keep spinning"}]},{"type":"text","value":"\n"},{"type":"element","tagName":"li","properties":{},"children":[{"type":"text","value":"Add water to get desired consistence"}]},{"type":"text","value":"\n"},{"type":"element","tagName":"li","properties":{},"children":[{"type":"text","value":"Add cumin, cayenne, salt, and pepper to taste"}]},{"type":"text","value":"\n"},{"type":"element","tagName":"li","properties":{},"children":[{"type":"text","value":"Garnish with sesame, and serve in a bowl with nachos or veggie sticks "}]},{"type":"text","value":"\n"}]}],"data":{"quirksMode":false}},"headings":[{"value":"Ingredients"},{"value":"Instructions"}],"frontmatter":{"path":"/recipes/redbeet-hummus","title":"Redbeet Hummus","author":"Jasper Meyer","date":"2019-05-12"}}},"pageContext":{"isCreatedByStatefulCreatePages":false,"dir":"recipes","section":"recipe"}}